unhashable/__init__.py
unhashable/__main__.py
unhashable/tests/__init__.py
unhashable/tests/test_1984.py
unhashable-0.0.0.dev0.dist-info/LICENSE.txt
unhashable-0.0.0.dev0.dist-info/METADATA
unhashable-0.0.0.dev0.dist-info/WHEEL
unhashable-0.0.0.dev0.dist-info/top_level.txt
unhashable-0.0.0.dev0.dist-info/RECORD
