Metadata-Version: 2.1
Name: unhashable
Version: 0.0.0.dev0
Summary: unhashable
Author-email: Johannes <johannes-programming@mailfence.com>
License: The MIT License (MIT)
Project-URL: Documentation, https://pypi.org/project/unhashable
Project-URL: Download, https://pypi.org/project/unhashable/#files
Project-URL: Source, https://github.com/johannes-programming/unhashable
Classifier: Development Status :: 1 - Planning
Classifier: License :: OSI Approved :: MIT License
Classifier: Programming Language :: Python
Classifier: Programming Language :: Python :: 3
Classifier: Programming Language :: Python :: 3 :: Only
Requires-Python: >=3.12.5
License-File: LICENSE.txt
